xingong_pypack/__init__.py
xingong_pypack/common.py
xingong_pypack/mapping.py
xingong_pypack/model.py
xingong_pypack/xingong_pypack.py
xingong_pypack-0.0.4.dist-info/LICENSE
xingong_pypack-0.0.4.dist-info/METADATA
xingong_pypack-0.0.4.dist-info/WHEEL
xingong_pypack-0.0.4.dist-info/entry_points.txt
xingong_pypack-0.0.4.dist-info/top_level.txt
xingong_pypack-0.0.4.dist-info/RECORD
